<?xml version='1.0' encoding='UTF-8'?>
<hudson.plugins.disk__usage.ProjectDiskUsage plugin="disk-usage@0.25">
  <diskUsageWithoutBuilds>240784</diskUsageWithoutBuilds>
  <slaveWorkspacesUsage class="concurrent-hash-map">
    <entry>
      <string></string>
      <concurrent-hash-map>
        <entry>
          <string>/opt/hudson/buildouts/www.eea.europa.eu-hudson</string>
          <long>2437051797</long>
        </entry>
      </concurrent-hash-map>
    </entry>
  </slaveWorkspacesUsage>
  <buildDiskUsage>
    <hudson.plugins.disk__usage.DiskUsageBuildInformation>
      <id>2015-02-12_06-07-59</id>
      <timestamp>1423717679000</timestamp>
      <number>581</number>
      <size>0</size>
    </hudson.plugins.disk__usage.DiskUsageBuildInformation>
    <hudson.plugins.disk__usage.DiskUsageBuildInformation>
      <id>2015-02-18_06-07-56</id>
      <timestamp>1424236076000</timestamp>
      <number>585</number>
      <size>0</size>
    </hudson.plugins.disk__usage.DiskUsageBuildInformation>
    <hudson.plugins.disk__usage.DiskUsageBuildInformation>
      <id>2015-02-16_06-08-14</id>
      <timestamp>1424063294000</timestamp>
      <number>583</number>
      <size>0</size>
    </hudson.plugins.disk__usage.DiskUsageBuildInformation>
    <hudson.plugins.disk__usage.DiskUsageBuildInformation>
      <id>597</id>
      <timestamp>1425878605903</timestamp>
      <number>597</number>
      <size>24350</size>
    </hudson.plugins.disk__usage.DiskUsageBuildInformation>
    <hudson.plugins.disk__usage.DiskUsageBuildInformation>
      <id>590</id>
      <timestamp>1424928188367</timestamp>
      <number>590</number>
      <size>24096</size>
    </hudson.plugins.disk__usage.DiskUsageBuildInformation>
    <hudson.plugins.disk__usage.DiskUsageBuildInformation>
      <id>598</id>
      <timestamp>1425964986852</timestamp>
      <number>598</number>
      <size>24402</size>
    </hudson.plugins.disk__usage.DiskUsageBuildInformation>
    <hudson.plugins.disk__usage.DiskUsageBuildInformation>
      <id>601</id>
      <timestamp>1426221474512</timestamp>
      <number>601</number>
      <size>24589</size>
    </hudson.plugins.disk__usage.DiskUsageBuildInformation>
    <hudson.plugins.disk__usage.DiskUsageBuildInformation>
      <id>592</id>
      <timestamp>1425273823353</timestamp>
      <number>592</number>
      <size>24229</size>
    </hudson.plugins.disk__usage.DiskUsageBuildInformation>
    <hudson.plugins.disk__usage.DiskUsageBuildInformation>
      <id>594</id>
      <timestamp>1425446599191</timestamp>
      <number>594</number>
      <size>24433</size>
    </hudson.plugins.disk__usage.DiskUsageBuildInformation>
    <hudson.plugins.disk__usage.DiskUsageBuildInformation>
      <id>2015-02-18_11-12-40</id>
      <timestamp>1424254360000</timestamp>
      <number>586</number>
      <size>0</size>
    </hudson.plugins.disk__usage.DiskUsageBuildInformation>
    <hudson.plugins.disk__usage.DiskUsageBuildInformation>
      <id>596</id>
      <timestamp>1425619680862</timestamp>
      <number>596</number>
      <size>24379</size>
    </hudson.plugins.disk__usage.DiskUsageBuildInformation>
    <hudson.plugins.disk__usage.DiskUsageBuildInformation>
      <id>591</id>
      <timestamp>1425014874553</timestamp>
      <number>591</number>
      <size>24182</size>
    </hudson.plugins.disk__usage.DiskUsageBuildInformation>
    <hudson.plugins.disk__usage.DiskUsageBuildInformation>
      <id>2015-02-20_06-13-18</id>
      <timestamp>1424409198000</timestamp>
      <number>588</number>
      <size>0</size>
    </hudson.plugins.disk__usage.DiskUsageBuildInformation>
    <hudson.plugins.disk__usage.DiskUsageBuildInformation>
      <id>599</id>
      <timestamp>1426051400143</timestamp>
      <number>599</number>
      <size>24388</size>
    </hudson.plugins.disk__usage.DiskUsageBuildInformation>
    <hudson.plugins.disk__usage.DiskUsageBuildInformation>
      <id>595</id>
      <timestamp>1425532998082</timestamp>
      <number>595</number>
      <size>24416</size>
    </hudson.plugins.disk__usage.DiskUsageBuildInformation>
    <hudson.plugins.disk__usage.DiskUsageBuildInformation>
      <id>2015-02-17_06-08-28</id>
      <timestamp>1424149708000</timestamp>
      <number>584</number>
      <size>0</size>
    </hudson.plugins.disk__usage.DiskUsageBuildInformation>
    <hudson.plugins.disk__usage.DiskUsageBuildInformation>
      <id>2015-02-19_06-08-04</id>
      <timestamp>1424322484000</timestamp>
      <number>587</number>
      <size>0</size>
    </hudson.plugins.disk__usage.DiskUsageBuildInformation>
    <hudson.plugins.disk__usage.DiskUsageBuildInformation>
      <id>600</id>
      <timestamp>1426134980408</timestamp>
      <number>600</number>
      <size>24399</size>
    </hudson.plugins.disk__usage.DiskUsageBuildInformation>
    <hudson.plugins.disk__usage.DiskUsageBuildInformation>
      <id>589</id>
      <timestamp>1424893696718</timestamp>
      <number>589</number>
      <size>24380</size>
    </hudson.plugins.disk__usage.DiskUsageBuildInformation>
    <hudson.plugins.disk__usage.DiskUsageBuildInformation>
      <id>2015-02-11_06-08-06</id>
      <timestamp>1423631286000</timestamp>
      <number>580</number>
      <size>0</size>
    </hudson.plugins.disk__usage.DiskUsageBuildInformation>
    <hudson.plugins.disk__usage.DiskUsageBuildInformation>
      <id>593</id>
      <timestamp>1425360191508</timestamp>
      <number>593</number>
      <size>24170</size>
    </hudson.plugins.disk__usage.DiskUsageBuildInformation>
    <hudson.plugins.disk__usage.DiskUsageBuildInformation>
      <id>2015-02-13_06-13-34</id>
      <timestamp>1423804414000</timestamp>
      <number>582</number>
      <size>0</size>
    </hudson.plugins.disk__usage.DiskUsageBuildInformation>
  </buildDiskUsage>
</hudson.plugins.disk__usage.ProjectDiskUsage>