<?xml version='1.0' encoding='UTF-8'?>
<hudson.plugins.disk__usage.ProjectDiskUsage plugin="disk-usage@0.25">
  <diskUsageWithoutBuilds>5827607</diskUsageWithoutBuilds>
  <slaveWorkspacesUsage class="concurrent-hash-map">
    <entry>
      <string></string>
      <concurrent-hash-map>
        <entry>
          <string>/opt/hudson/buildouts/www.eea.europa.eu-hudson/src/Products.EEAContentTypes</string>
          <long>13391107</long>
        </entry>
      </concurrent-hash-map>
    </entry>
  </slaveWorkspacesUsage>
  <buildDiskUsage>
    <hudson.plugins.disk__usage.DiskUsageBuildInformation>
      <id>2426</id>
      <timestamp>1425618337570</timestamp>
      <number>2426</number>
      <size>420134</size>
    </hudson.plugins.disk__usage.DiskUsageBuildInformation>
    <hudson.plugins.disk__usage.DiskUsageBuildInformation>
      <id>2431</id>
      <timestamp>1426089311150</timestamp>
      <number>2431</number>
      <size>419711</size>
    </hudson.plugins.disk__usage.DiskUsageBuildInformation>
    <hudson.plugins.disk__usage.DiskUsageBuildInformation>
      <id>2429</id>
      <timestamp>1425963764851</timestamp>
      <number>2429</number>
      <size>420092</size>
    </hudson.plugins.disk__usage.DiskUsageBuildInformation>
    <hudson.plugins.disk__usage.DiskUsageBuildInformation>
      <id>2433</id>
      <timestamp>1426220271852</timestamp>
      <number>2433</number>
      <size>420093</size>
    </hudson.plugins.disk__usage.DiskUsageBuildInformation>
    <hudson.plugins.disk__usage.DiskUsageBuildInformation>
      <id>2421</id>
      <timestamp>1425013551870</timestamp>
      <number>2421</number>
      <size>420418</size>
    </hudson.plugins.disk__usage.DiskUsageBuildInformation>
    <hudson.plugins.disk__usage.DiskUsageBuildInformation>
      <id>2015-02-17_06-20-08</id>
      <timestamp>1424150408000</timestamp>
      <number>2415</number>
      <size>0</size>
    </hudson.plugins.disk__usage.DiskUsageBuildInformation>
    <hudson.plugins.disk__usage.DiskUsageBuildInformation>
      <id>2015-02-11_06-20-11</id>
      <timestamp>1423632011000</timestamp>
      <number>2411</number>
      <size>0</size>
    </hudson.plugins.disk__usage.DiskUsageBuildInformation>
    <hudson.plugins.disk__usage.DiskUsageBuildInformation>
      <id>2423</id>
      <timestamp>1425358973158</timestamp>
      <number>2423</number>
      <size>420121</size>
    </hudson.plugins.disk__usage.DiskUsageBuildInformation>
    <hudson.plugins.disk__usage.DiskUsageBuildInformation>
      <id>2015-02-19_06-19-52</id>
      <timestamp>1424323192000</timestamp>
      <number>2417</number>
      <size>0</size>
    </hudson.plugins.disk__usage.DiskUsageBuildInformation>
    <hudson.plugins.disk__usage.DiskUsageBuildInformation>
      <id>2015-02-12_06-19-58</id>
      <timestamp>1423718398000</timestamp>
      <number>2412</number>
      <size>0</size>
    </hudson.plugins.disk__usage.DiskUsageBuildInformation>
    <hudson.plugins.disk__usage.DiskUsageBuildInformation>
      <id>2419</id>
      <timestamp>1424892543820</timestamp>
      <number>2419</number>
      <size>420338</size>
    </hudson.plugins.disk__usage.DiskUsageBuildInformation>
    <hudson.plugins.disk__usage.DiskUsageBuildInformation>
      <id>2427</id>
      <timestamp>1425877389290</timestamp>
      <number>2427</number>
      <size>420083</size>
    </hudson.plugins.disk__usage.DiskUsageBuildInformation>
    <hudson.plugins.disk__usage.DiskUsageBuildInformation>
      <id>2430</id>
      <timestamp>1426050162664</timestamp>
      <number>2430</number>
      <size>420041</size>
    </hudson.plugins.disk__usage.DiskUsageBuildInformation>
    <hudson.plugins.disk__usage.DiskUsageBuildInformation>
      <id>2015-02-18_06-19-45</id>
      <timestamp>1424236785000</timestamp>
      <number>2416</number>
      <size>0</size>
    </hudson.plugins.disk__usage.DiskUsageBuildInformation>
    <hudson.plugins.disk__usage.DiskUsageBuildInformation>
      <id>2015-02-16_06-20-16</id>
      <timestamp>1424064016000</timestamp>
      <number>2414</number>
      <size>0</size>
    </hudson.plugins.disk__usage.DiskUsageBuildInformation>
    <hudson.plugins.disk__usage.DiskUsageBuildInformation>
      <id>2428</id>
      <timestamp>1425916511485</timestamp>
      <number>2428</number>
      <size>419741</size>
    </hudson.plugins.disk__usage.DiskUsageBuildInformation>
    <hudson.plugins.disk__usage.DiskUsageBuildInformation>
      <id>2015-02-13_06-26-42</id>
      <timestamp>1423805202000</timestamp>
      <number>2413</number>
      <size>0</size>
    </hudson.plugins.disk__usage.DiskUsageBuildInformation>
    <hudson.plugins.disk__usage.DiskUsageBuildInformation>
      <id>2425</id>
      <timestamp>1425531780343</timestamp>
      <number>2425</number>
      <size>420078</size>
    </hudson.plugins.disk__usage.DiskUsageBuildInformation>
    <hudson.plugins.disk__usage.DiskUsageBuildInformation>
      <id>2422</id>
      <timestamp>1425272584577</timestamp>
      <number>2422</number>
      <size>420086</size>
    </hudson.plugins.disk__usage.DiskUsageBuildInformation>
    <hudson.plugins.disk__usage.DiskUsageBuildInformation>
      <id>2424</id>
      <timestamp>1425445366418</timestamp>
      <number>2424</number>
      <size>420047</size>
    </hudson.plugins.disk__usage.DiskUsageBuildInformation>
    <hudson.plugins.disk__usage.DiskUsageBuildInformation>
      <id>2432</id>
      <timestamp>1426133826363</timestamp>
      <number>2432</number>
      <size>420004</size>
    </hudson.plugins.disk__usage.DiskUsageBuildInformation>
    <hudson.plugins.disk__usage.DiskUsageBuildInformation>
      <id>2015-02-20_06-26-32</id>
      <timestamp>1424409992000</timestamp>
      <number>2418</number>
      <size>0</size>
    </hudson.plugins.disk__usage.DiskUsageBuildInformation>
    <hudson.plugins.disk__usage.DiskUsageBuildInformation>
      <id>2420</id>
      <timestamp>1424926965203</timestamp>
      <number>2420</number>
      <size>195720</size>
    </hudson.plugins.disk__usage.DiskUsageBuildInformation>
  </buildDiskUsage>
</hudson.plugins.disk__usage.ProjectDiskUsage>